PySimplePolls/SimplePolls.py
PySimplePolls/__init__.py
PySimplePolls-1.0.0.dist-info/LICENSE
PySimplePolls-1.0.0.dist-info/METADATA
PySimplePolls-1.0.0.dist-info/WHEEL
PySimplePolls-1.0.0.dist-info/top_level.txt
PySimplePolls-1.0.0.dist-info/RECORD
